hdp/__init__.py
hdp-0.3.dist-info/METADATA
hdp-0.3.dist-info/WHEEL
hdp-0.3.dist-info/top_level.txt
hdp-0.3.dist-info/RECORD
