Metadata-Version: 2.1
Name: hdp
Version: 0.3
Summary: Implementation of Hierarchical LDA
Home-page: http://github.com/datadiarist/hdp
Author: Andrew and Eduardo
Author-email: andrew.carr@duke.edu
License: MIT
Platform: UNKNOWN
